Metadata-Version: 2.1
Name: lambdata-cocoisland
Version: 0.0.9
Summary: A collection of Data Science helper functions
Home-page: https://github.com/cocoisland
Author: cocoisland
License: UNKNOWN
Platform: UNKNOWN
Classifier: Programming Language :: Python :: 3
Classifier: License :: OSI Approved :: MIT License
Classifier: Operating System :: OS Independent
Requires-Python: >=3.5
